nisanyan_cli/__init__.py
nisanyan_cli/__main__.py
nisanyan_cli/_adlar_cache.py
nisanyan_cli/_langlist.py
nisanyan_cli/_utils.py
nisanyan_cli/adlar.py
nisanyan_cli/cli.py
nisanyan_cli/request.py
nisanyan_cli/tree.py
nisanyan_cli-0.4.5.dist-info/METADATA
nisanyan_cli-0.4.5.dist-info/WHEEL
nisanyan_cli-0.4.5.dist-info/entry_points.txt
nisanyan_cli-0.4.5.dist-info/RECORD
