Metadata-Version: 2.4
Name: nisanyan-cli
Version: 0.4.5
Summary: CLI tool for Turkish etymological dictionary, nisanyansozluk.com (nis <word>)
Project-URL: Homepage, https://github.com/agmmnn/nisanyan-cli
Project-URL: Repository, https://github.com/agmmnn/nisanyan-cli
Project-URL: Changelog, https://github.com/agmmnn/nisanyan-cli/releases
Project-URL: Bug Tracker, https://github.com/agmmnn/nisanyan-cli/issues
Author-email: Gökçe <agmmnn@gmail.com>
Keywords: antonym,cli,synonym,thesaurus
Classifier: Environment :: Console
Classifier: Operating System :: OS Independent
Classifier: Programming Language :: Python :: 3
Classifier: Topic :: Utilities
Requires-Python: >=3.8
Requires-Dist: importlib-metadata>=6.8.0
Requires-Dist: rich>=13.6.0
